{"0": {"task_finish_time": 245, "total_battery_consume": 1885, "charge_waiting_time": 1, "respond_failing_time": 1707},"1": {"task_finish_time": 278, "total_battery_consume": 2192, "charge_waiting_time": 0, "respond_failing_time": 1769},"2": {"task_finish_time": 293, "total_battery_consume": 2268, "charge_waiting_time": 2, "respond_failing_time": 2247},"3": {"task_finish_time": 252, "total_battery_consume": 1957, "charge_waiting_time": 0, "respond_failing_time": 2222},"4": {"task_finish_time": 164, "total_battery_consume": 1279, "charge_waiting_time": 0, "respond_failing_time": 1328},"5": {"task_finish_time": 293, "total_battery_consume": 2312, "charge_waiting_time": 1, "respond_failing_time": 1856},"6": {"task_finish_time": 431, "total_battery_consume": 3425, "charge_waiting_time": 8, "respond_failing_time": 2456},"7": {"task_finish_time": 261, "total_battery_consume": 2044, "charge_waiting_time": 0, "respond_failing_time": 1866},"8": {"task_finish_time": 245, "total_battery_consume": 1934, "charge_waiting_time": 1, "respond_failing_time": 1776},"9": {"task_finish_time": 420, "total_battery_consume": 3272, "charge_waiting_time": 1, "respond_failing_time": 2047},"10": {"task_finish_time": 261, "total_battery_consume": 2014, "charge_waiting_time": 0, "respond_failing_time": 2292},"11": {"task_finish_time": 385, "total_battery_consume": 3002, "charge_waiting_time": 1, "respond_failing_time": 1952},"12": {"task_finish_time": 245, "total_battery_consume": 1873, "charge_waiting_time": 2, "respond_failing_time": 1771},"13": {"task_finish_time": 266, "total_battery_consume": 2104, "charge_waiting_time": 0, "respond_failing_time": 2282},"14": {"task_finish_time": 383, "total_battery_consume": 2992, "charge_waiting_time": 1, "respond_failing_time": 2133},"15": {"task_finish_time": 387, "total_battery_consume": 3058, "charge_waiting_time": 1, "respond_failing_time": 2300},"16": {"task_finish_time": 222, "total_battery_consume": 1765, "charge_waiting_time": 0, "respond_failing_time": 1767},"17": {"task_finish_time": 432, "total_battery_consume": 3429, "charge_waiting_time": 2, "respond_failing_time": 2552}